ml/__init__.py
ml/audio_instance.py
ml/classification.py
ml/data_import.py
ml/data_processing.py
ml/opensmile.py
ml/results_processing.py
ml/signal_processing.py
ml/system.py
ml/utils.py
ml/visualizations.py
ml/feature_extraction/__init__.py
ml/feature_extraction/extractors.py
ml/feature_extraction/feature_extraction.py
ml/feature_extraction/audio/__init__.py
ml/feature_extraction/audio/acoustics_extractor.py
ml/feature_extraction/audio/intensity_extractor.py
ml/feature_extraction/audio/pitch_extractor.py
ml/feature_extraction/audio/tt_features_extractor.py
ml/feature_extraction/audio/voice-analysis-voiced.praat
ml/feature_extraction/audio/voice-analysis.praat
ml/feature_extraction/audio/voice_quality_extractor.py
ml/feature_extraction/eeg/__init__.py
ml/feature_extraction/eeg/eeg_feature_extractor.py
ml/feature_extraction/eeg/freq_extractor.py
ml/feature_extraction/eeg/raw_extractor.py
ml/feature_extraction/eeg/trash_extractor.py
ml/feature_extraction/eeg/wavelets_extractor.py
ml/feature_extraction/eeg/windowed_extractor.py
ml/parsing/__init__.py
ml/parsing/arff.py
ml/parsing/equality.py
ml/parsing/intervals.py
ml/parsing/textgrid.py
ml/parsing/turn.py
ml/parsing/wavesurfer.py
ml_eeg-0.0.62.dist-info/DESCRIPTION.rst
ml_eeg-0.0.62.dist-info/METADATA
ml_eeg-0.0.62.dist-info/RECORD
ml_eeg-0.0.62.dist-info/WHEEL
ml_eeg-0.0.62.dist-info/metadata.json
ml_eeg-0.0.62.dist-info/top_level.txt
tests/__init__.py
tests/feature_extraction/__init__.py
tests/feature_extraction/audio/__init__.py
tests/feature_extraction/audio/test_acoustics_extractor.py
