Metadata-Version: 2.0
Name: ml-eeg
Version: 0.0.62
Summary: A ml & eeg helper library
Home-page: https://github.com/pbrusco/ml-eeg/
Author: Pablo Brusco
Author-email: pbrusco@dc.uba.ar
License: GPLv3
Keywords: eeg ml
Platform: UNKNOWN
Classifier: Development Status :: 3 - Alpha
Classifier: Intended Audience :: Developers
Classifier: Topic :: Software Development :: Build Tools
Classifier: License :: OSI Approved :: GNU General Public License v3 (GPLv3)
Classifier: Programming Language :: Python :: 3
Requires-Dist: liac-arff
Requires-Dist: tabulate
Requires-Dist: pydub
Provides-Extra: test
Requires-Dist: coverage; extra == 'test'
